jnj-lib-doc/test.py
jnj_lib_base/basic.py
jnj_lib_base/builtin.py
jnj_lib_base/time.py
jnj_lib_test1-0.0.1.dist-info/METADATA
jnj_lib_test1-0.0.1.dist-info/WHEEL
jnj_lib_test1-0.0.1.dist-info/top_level.txt
jnj_lib_test1-0.0.1.dist-info/RECORD
